.VERSION
AUTHORS.rst
CONTRIBUTING.rst
HISTORY.rst
LICENSE
MANIFEST.in
Pipfile
Pipfile.lock
README.rst
USAGE.rst
dev-requirements.txt
requirements.txt
setup.cfg
setup.py
docs/Makefile
docs/authors.rst
docs/conf.py
docs/contributing.rst
docs/history.rst
docs/index.rst
docs/installation.rst
docs/readme.rst
docs/usage.rst
powermolecli/.VERSION
powermolecli/AUTHORS.rst
powermolecli/CONTRIBUTING.rst
powermolecli/HISTORY.rst
powermolecli/LICENSE
powermolecli/Pipfile
powermolecli/Pipfile.lock
powermolecli/README.rst
powermolecli/USAGE.rst
powermolecli/__init__.py
powermolecli/_version.py
powermolecli/dev-requirements.txt
powermolecli/powermolecli.py
powermolecli/powermolecliexceptions.py
powermolecli/requirements.txt
powermolecli.egg-info/PKG-INFO
powermolecli.egg-info/SOURCES.txt
powermolecli.egg-info/dependency_links.txt
powermolecli.egg-info/entry_points.txt
powermolecli.egg-info/not-zip-safe
powermolecli.egg-info/requires.txt
powermolecli.egg-info/top_level.txt
powermolecli/lib/__init__.py
powermolecli/lib/helpers.py
powermolecli/lib/logging.py
tests/test_powermolecli.py