Metadata-Version: 2.1
Name: powermolecli
Version: 1.0.16
Summary: powermole(cli) allows you to connect to a target destination host via one or more intermediaries, offering a variety of modes (FOR and TOR) and options (TRANSFER and COMMAND) to perform a variety of tasks
Home-page: https://github.com/yutanicorp/powermolecli
Author: Vincent Schouten
Author-email: powermole@protonmail.com
License: MIT
Keywords: powermole powermolecli ssh proxyjump forwarding tor cli
Classifier: Development Status :: 4 - Beta
Classifier: Intended Audience :: Developers
Classifier: License :: OSI Approved :: MIT License
Classifier: Natural Language :: English
Classifier: Programming Language :: Python :: 3.7
Classifier: Topic :: System :: Networking
Classifier: Topic :: Security
Classifier: Topic :: Internet
Classifier: Environment :: Console
Classifier: Operating System :: MacOS
Classifier: Operating System :: POSIX
License-File: LICENSE
License-File: AUTHORS.rst
